recognize.py
m_recognize-0.1.dist-info/LICENSE
m_recognize-0.1.dist-info/METADATA
m_recognize-0.1.dist-info/WHEEL
m_recognize-0.1.dist-info/top_level.txt
m_recognize-0.1.dist-info/RECORD
